.gitignore
setup.py
nearset/__init__.c
nearset/__init__.pyx
nearset/metrics.c
nearset/metrics.pyx
nearset.egg-info/PKG-INFO
nearset.egg-info/SOURCES.txt
nearset.egg-info/dependency_links.txt
nearset.egg-info/requires.txt
nearset.egg-info/top_level.txt
tests/euclidean_metric.py
tests/hello_world.py