Metadata-Version: 2.1
Name: nearset
Version: 0.0.5
Summary: Efficient ordered set of elements with custom comparator function in Python
Home-page: https://github.com/kerighan/nearset
Author: Maixent Chenebaux
Author-email: max.chbx@gmail.com
License: UNKNOWN
Platform: UNKNOWN
Classifier: Programming Language :: Python :: 3
Classifier: Programming Language :: Python :: 3.7
Classifier: License :: OSI Approved :: MIT License
Classifier: Operating System :: OS Independent
Requires-Python: >=3.5
